src/__init__.py
src/__main__.py
src/kohaSync.py
src/commands/BaseCommand.py
src/commands/LoadConfigFileCommand.py
src/commands/SyncKohaRowsCommand.py
src/commands/ValidateApiCommand.py
src/commands/ValidateKohaDBCommand.py
src/commands/ValidateRequirementsCommand.py
src/commands/__init__.py
src/core/Config.py
src/core/DBPool.py
src/core/Models.py
src/core/SqlSentences.py
src/core/__init__.py
src/utils/CacheManager.py
src/utils/FakeHeaders.py
src/utils/Logger.py
src/utils/Singleton.py
src/utils/__init__.py
koha_sync-1.2.5.dist-info/METADATA
koha_sync-1.2.5.dist-info/WHEEL
koha_sync-1.2.5.dist-info/entry_points.txt
koha_sync-1.2.5.dist-info/top_level.txt
koha_sync-1.2.5.dist-info/RECORD
