Metadata-Version: 2.1
Name: koha-sync
Version: 1.2.5
Summary: This projects allows to synchronize remote Koha rows to an endpoint
Home-page: https://jaguirre_referencistas@bitbucket.org/jaguirre_referencistas/koha_synchronizer.git
Author: Juan Pablo Aguirre
Author-email: jaguirre@referencistas.com
License: MIT
Platform: UNKNOWN
Requires-Python: >=2.7
Requires-Dist: click
Requires-Dist: tqdm
Requires-Dist: jsonschema
Requires-Dist: requests
Requires-Dist: pymysql
Requires-Dist: loguru
Requires-Dist: diskcache
Requires-Dist: setuptools
Requires-Dist: wheel
Requires-Dist: pyyaml
